cubicweb_searchui/__init__.py
cubicweb_searchui/__pkginfo__.py
cubicweb_searchui/entities.py
cubicweb_searchui/hooks.py
cubicweb_searchui/schema.py
cubicweb_searchui/uiprops.py
cubicweb_searchui/data/cubes.searchui.bundle.css
cubicweb_searchui/data/cubes.searchui.bundle.js
cubicweb_searchui/data/cubes.searchui.css
cubicweb_searchui/data/cubes.searchui.facets.js
cubicweb_searchui/i18n/en.po
cubicweb_searchui/i18n/es.po
cubicweb_searchui/i18n/fr.po
cubicweb_searchui/migration/0.2.0_Any.py
cubicweb_searchui/migration/postcreate.py
cubicweb_searchui/views/__init__.py
cubicweb_searchui/views/relswitch.py
cubicweb_searchui/views/search.py
cubicweb_searchui-1.1.0.dist-info/METADATA
cubicweb_searchui-1.1.0.dist-info/WHEEL
cubicweb_searchui-1.1.0.dist-info/entry_points.txt
cubicweb_searchui-1.1.0.dist-info/top_level.txt
cubicweb_searchui-1.1.0.dist-info/RECORD
